{
  "start_time": "2026-07-16T16:19:51.695621+00:00",
  "start_equity": 1000.0,
  "equity": 999.3158528517605,
  "realized_pnl": -0.6841471482395073,
  "last_acted_candle": "2026-07-17T03:00:00+00:00",
  "position": {
    "side": "SHORT",
    "entry_time": "2026-07-17T04:03:08.312740+00:00",
    "entry_candle": "2026-07-17T03:00:00+00:00",
    "entry_px": 0.072268,
    "qty": 15777.979716,
    "notional": 1140.25,
    "size_mult": 1.14,
    "scheduled_exit_candle": "2026-07-20T03:00:00+00:00",
    "ref_levels": {
      "minus10": 0.078606,
      "minus20": 0.084944
    }
  },
  "trades": [],
  "equity_curve": [
    {
      "t": "2026-07-16T15:00:00+00:00",
      "eq": 1000.0,
      "px": 0.073484
    },
    {
      "t": "2026-07-16T15:00:00+00:00",
      "eq": 1000.0,
      "px": 0.073357
    },
    {
      "t": "2026-07-16T16:00:00+00:00",
      "eq": 1000.0,
      "px": 0.07332
    },
    {
      "t": "2026-07-16T17:00:00+00:00",
      "eq": 1000.0,
      "px": 0.073204
    },
    {
      "t": "2026-07-16T17:00:00+00:00",
      "eq": 1000.0,
      "px": 0.07354
    },
    {
      "t": "2026-07-16T17:00:00+00:00",
      "eq": 1000.0,
      "px": 0.073436
    },
    {
      "t": "2026-07-16T18:00:00+00:00",
      "eq": 1000.0,
      "px": 0.07345
    },
    {
      "t": "2026-07-16T19:00:00+00:00",
      "eq": 1000.0,
      "px": 0.073146
    },
    {
      "t": "2026-07-16T20:00:00+00:00",
      "eq": 1000.0,
      "px": 0.072955
    },
    {
      "t": "2026-07-16T21:00:00+00:00",
      "eq": 1000.0,
      "px": 0.073203
    },
    {
      "t": "2026-07-16T22:00:00+00:00",
      "eq": 1000.0,
      "px": 0.072712
    },
    {
      "t": "2026-07-16T23:00:00+00:00",
      "eq": 1000.0,
      "px": 0.0723
    },
    {
      "t": "2026-07-17T00:00:00+00:00",
      "eq": 1000.0,
      "px": 0.07273
    },
    {
      "t": "2026-07-17T01:00:00+00:00",
      "eq": 1000.0,
      "px": 0.072162
    },
    {
      "t": "2026-07-17T02:00:00+00:00",
      "eq": 1000.0,
      "px": 0.07211
    },
    {
      "t": "2026-07-17T03:00:00+00:00",
      "eq": 999.32,
      "px": 0.072268
    },
    {
      "t": "2026-07-17T04:00:00+00:00",
      "eq": 1002.19,
      "px": 0.072086
    },
    {
      "t": "2026-07-17T05:00:00+00:00",
      "eq": 1011.28,
      "px": 0.07151
    },
    {
      "t": "2026-07-17T06:00:00+00:00",
      "eq": 1007.05,
      "px": 0.071778
    },
    {
      "t": "2026-07-17T07:00:00+00:00",
      "eq": 1007.89,
      "px": 0.071724
    },
    {
      "t": "2026-07-17T08:00:00+00:00",
      "eq": 1012.85,
      "px": 0.07141
    },
    {
      "t": "2026-07-17T09:00:00+00:00",
      "eq": 1007.14,
      "px": 0.071772
    }
  ],
  "halted": false
}